Metadata-Version: 2.4
Name: gmicloud
Version: 0.1.10
Summary: GMI Cloud Python SDK
Author-email: GMI <gmi@gmitec.net>
License: MIT
Classifier: Programming Language :: Python :: 3
Classifier: License :: OSI Approved :: MIT License
Classifier: Operating System :: OS Independent
Requires-Python: >=3.6
